fuzzy_rank_ensemble_torch/__init__.py
fuzzy_rank_ensemble_torch/fuzzy_ensemble.py
fuzzy_rank_ensemble_torch/monai/__init__.py
fuzzy_rank_ensemble_torch/monai/fuzzy_ensemble.py
fuzzy_rank_ensemble_torch-0.1.1.dist-info/METADATA
fuzzy_rank_ensemble_torch-0.1.1.dist-info/WHEEL
fuzzy_rank_ensemble_torch-0.1.1.dist-info/licenses/LICENSE
fuzzy_rank_ensemble_torch-0.1.1.dist-info/RECORD
