Metadata-Version: 2.4
Name: fuzzy-rank-ensemble-torch
Version: 0.1.1
Summary: A torch based package for fuzzy rank based ensembles
License-Expression: Apache-2.0
License-File: LICENSE
Author: Aleksandr Sinitca
Author-email: amsinitca@etu.ru
Requires-Python: >=3.10
Classifier: Programming Language :: Python :: 3
Classifier: Programming Language :: Python :: 3.10
Classifier: Programming Language :: Python :: 3.11
Classifier: Programming Language :: Python :: 3.12
Classifier: Programming Language :: Python :: 3.13
Classifier: Programming Language :: Python :: 3.14
Provides-Extra: monai
Requires-Dist: monai (>=1.3,<2.0) ; extra == "monai"
Requires-Dist: torch (>=2.2.2,<3.0.0)
